README.rst
setup.py
ppxml/__init__.py
ppxml.egg-info/PKG-INFO
ppxml.egg-info/SOURCES.txt
ppxml.egg-info/dependency_links.txt
ppxml.egg-info/entry_points.txt
ppxml.egg-info/requires.txt
ppxml.egg-info/top_level.txt