Metadata-Version: 1.0
Name: ppxml
Version: 0.1.0
Summary: Command-line tool pretty-print XML with xpath
Home-page: https://github.com/h2rd/ppxml
Author: Igor Skrynkovskyy
Author-email: skrynkovskyy@gmail.com
License: MIT
Keywords: xml
Platform: UNKNOWN
